pms_utils.cpython-310-x86_64-linux-gnu.so
pms_utils/__init__.pyi
pms_utils/atom.pyi
pms_utils/depend.pyi
pms_utils/ebuild.pyi
pms_utils/profile.pyi
pms_utils/py.typed
pms_utils/repo.pyi
pms_utils/vdb.pyi
pms_utils-0.5.4.dist-info/METADATA
pms_utils-0.5.4.dist-info/WHEEL
pms_utils-0.5.4.dist-info/RECORD
