Metadata-Version: 2.1
Name: pms-utils
Version: 0.5.4
Summary: A helper library to implement the Gentoo Package Manager Specification
Project-URL: source, https://github.com/Jannik2099/pms-utils
Project-URL: documentation, https://pms-utils.pages.dev
Requires-Python: >=3.8
Requires-Dist: typing-extensions; python_version < "3.11"
